Metadata-Version: 2.1
Name: siwp2005-feliciano-sort
Version: 0.1.0
Summary: A collection of sorting algorithms
Home-page: https://github.com/yourusername/siwp2005-feliciano-sort
Author: Feliciano
Author-email: your-email@example.com
License: UNKNOWN
Platform: UNKNOWN
Classifier: Programming Language :: Python :: 3
Classifier: License :: OSI Approved :: MIT License
Classifier: Operating System :: OS Independent
Requires-Python: >=3.6
License-File: LICENSE
